eks_cluster_manager/__init__.py
eks_cluster_manager/auth.py
eks_cluster_manager/aws-iam-authenticator
eks_cluster_manager/index.py
eks_cluster_manager/kubeconfig.py
eks_cluster_manager/kubectl.py
eks_cluster_manager/test.py
eks_cluster_manager-1.0.dist-info/METADATA
eks_cluster_manager-1.0.dist-info/WHEEL
eks_cluster_manager-1.0.dist-info/top_level.txt
eks_cluster_manager-1.0.dist-info/RECORD
