Metadata-Version: 2.1
Name: eks-cluster-manager
Version: 1.0
Summary: Manage AWS EKS with Cloudformation
Home-page: http://github.com/droidlabour
Author: Joy Prakash Sharma
Author-email: droidlabour@gmail.com
License: MIT
Platform: UNKNOWN
Classifier: Development Status :: 3 - Alpha
Classifier: License :: OSI Approved :: MIT License
Classifier: Programming Language :: Python :: 3.7
Requires-Dist: boto3 (==1.9.130)
Requires-Dist: kubernetes
Requires-Dist: pyyaml
